Metadata-Version: 1.1
Name: scrapy-loaders
Version: 0.0.5
Summary: Scrapy Database Loader Wrapper with SQLAlchemy
Home-page: https://git.herrerosolis.com/Scrapers/scrapy_loaders
Author: Rafael Herrero Solis
Author-email: rafahsolis@hotmail.com
License: MIT license
Download-URL: https://git.herrerosolis.com/Scrapers/scrapy_loaders/-/archive/v0.0.5/scrapy_loaders-v0.0.5.tar.gz
Keywords: scrapy_loaders,Scrapy,SQLAlchemy
Platform: UNKNOWN
Classifier: License :: OSI Approved :: MIT License
Classifier: Development Status :: 3 - Alpha
Classifier: License :: OSI Approved :: Apache Software License
Classifier: Programming Language :: Python :: 3.6
